{"success":true,"result":{"Q_10108783298362-1":{"resources":[],"questions":[{"id":"Q_10108783298362-1","subjectId":101,"knowledgePoints":null,"knowledgePointsNew":[],"testMethods":[{"id":"TM_10100000672366","main":1}],"solutionMethods":[],"resourceIds":null,"resourceIndex":0,"listenUrl":null,"listenName":null,"listenSeconds":0,"exploreSeconds":0,"answersSeconds":0,"paperIds":["P_10100124324235-1","P_10100124324235-2","P_10100124324235-3"],"books":null,"booksNew":null,"contentTypeId":1010008,"contentType2Id":0,"difficultyInt":1,"description":"阅读文章，回答问题","notFitMobile":0,"seconds":480,"complex":1,"nid":null,"lastEditorId":null,"finalAuditorId":null,"roughAuditorIds":null,"content":{"content":"<p style=\"text-indent: 2em;\"><span style=\"text-decoration: underline;\">日内瓦的鸟也像野草般自由生息。</span>这里没人提笼架鸟，欲把天下珍奇鸟类都关进自家笼中独赏。从日内瓦湖中的白天鹅，到城内树林里的黑乌鸦，都有人投喂面包和巧克力，从未听说过偷捕和滥杀的事情发生。这里几乎所有的鸟都不怕人，一见有人喂食就飞来讨要。不少老人还每天定点定时去湖边喂鸟，鸟儿也准时来“赴宴”，在老人的指尖上啄食。日内瓦人把整座城市都营造成一个鸟儿的乐园。</p>","contentDesc":"","analysis":"","subContents":[{"content":"<p>联系上下文，根据解释写出文中的词语。</p><p>__$$__：去参加宴会，这里指鸟儿来吃食物。</p>","answers":[{"answer":"赴宴","subAnswers":["赴宴"],"richTexts":null,"scorePercentage":1,"classification":"","knowledgePoints":null,"knowledgePointsNew":[],"testMethods":[{"id":"TM_10100003182846","main":1}],"solutionMethods":[],"classificationListenUrl":null}],"subContentTypeId":4,"analysis":"","optionType":"word","options":[],"hideOptionNumber":0,"listenUrl":"","listenName":"","listenSeconds":0,"exploreSeconds":0,"answersSeconds":0,"oralDict":{"seconds":null,"variables":null,"keywords":null,"options":null,"voiceText":null,"sentencePatterns":null,"picUrl":null,"picName":null,"beginListenUrl":null,"endListenUrl":null,"scorePercentage":null,"readySeconds":null,"listenFile":null,"contentDesc":null,"answers":null,"voiceTextsNew":null,"jsgf":null,"videoUrl":null,"videoCoverUrl":null,"highlightPos":null},"submitWays":[0],"tags":[101007],"analysisList":null,"pictureUrl":"","extras":{},"tagsDesc":["其他"]},{"content":"<p>联系上下文，根据解释写出文中的词语。</p><p>__$$__：有计划、有目的地造。</p>","answers":[{"answer":"营造","subAnswers":["营造"],"richTexts":null,"scorePercentage":1,"classification":"","knowledgePoints":null,"knowledgePointsNew":[],"testMethods":[{"id":"TM_10100003182846","main":1}],"solutionMethods":[],"classificationListenUrl":null}],"subContentTypeId":4,"analysis":"","optionType":"word","options":[],"hideOptionNumber":0,"listenUrl":"","listenName":"","listenSeconds":0,"exploreSeconds":0,"answersSeconds":0,"oralDict":{"seconds":null,"variables":null,"keywords":null,"options":null,"voiceText":null,"sentencePatterns":null,"picUrl":null,"picName":null,"beginListenUrl":null,"endListenUrl":null,"scorePercentage":null,"readySeconds":null,"listenFile":null,"contentDesc":null,"answers":null,"voiceTextsNew":null,"jsgf":null,"videoUrl":null,"videoCoverUrl":null,"highlightPos":null},"submitWays":[0],"tags":[101007],"analysisList":null,"pictureUrl":"","extras":{},"tagsDesc":["其他"]},{"content":"<p>选择。</p><p>文中画线句是一个（　）句。</p>","answers":[{"answer":"1","subAnswers":[],"richTexts":null,"scorePercentage":1,"classification":"","knowledgePoints":null,"knowledgePointsNew":[],"testMethods":[],"solutionMethods":[],"classificationListenUrl":null}],"subContentTypeId":1,"analysis":"","optionType":"word","options":[{"option":"过渡","file":{"fileId":"","url":"","filename":"","seconds":0}},{"option":"总起","file":{"fileId":"","url":"","filename":"","seconds":0}}],"hideOptionNumber":0,"listenUrl":"","listenName":"","listenSeconds":0,"exploreSeconds":0,"answersSeconds":0,"oralDict":{"seconds":null,"variables":null,"keywords":null,"options":null,"voiceText":null,"sentencePatterns":null,"picUrl":null,"picName":null,"beginListenUrl":null,"endListenUrl":null,"scorePercentage":null,"readySeconds":null,"listenFile":null,"contentDesc":null,"answers":null,"voiceTextsNew":null,"jsgf":null,"videoUrl":null,"videoCoverUrl":null,"highlightPos":null},"submitWays":[0],"tags":[101007],"analysisList":null,"pictureUrl":"","extras":{},"tagsDesc":["其他"]}]},"docId":"Q_10108783298362","version":1,"wordId":null,"pictureUrl":null,"tagId":null,"createdAt":1501234035549,"deletedAt":null,"olCreatedAt":1501518640343,"olUpdatedAt":1509650995098,"sentenceIds":null,"sentenceContents":null,"practiceTypeIds":null,"categoryId":0,"fromId":7,"paragraph":null,"articleName":null,"descriptionFile":{"fileId":"","url":"","filename":"","seconds":0},"analysisSeconds":0,"readySeconds":0,"wikiType":null,"others":{"writing_style":"AC_20300000283078"},"skillIds":null,"weighted":null,"additions":null,"answers":[["赴宴"],["营造"],["1"]],"tags":[101007]}]}}}