{"success":true,"result":{"Q_10110621786524-2":{"resources":[],"questions":[{"id":"Q_10110621786524-2","subjectId":101,"knowledgePoints":null,"knowledgePointsNew":[],"testMethods":[{"id":"TM_10100000673226","main":1}],"solutionMethods":[],"resourceIds":null,"resourceIndex":0,"listenUrl":null,"listenName":null,"listenSeconds":0,"exploreSeconds":0,"answersSeconds":0,"paperIds":["P_10100140313034-3","P_10100140313034-4","P_10100140313034-5"],"books":null,"booksNew":null,"contentTypeId":1010008,"contentType2Id":0,"difficultyInt":4,"description":"阅读课外文章，回答问题","notFitMobile":0,"seconds":960,"complex":1,"nid":null,"lastEditorId":null,"finalAuditorId":null,"roughAuditorIds":null,"content":{"content":"<p style=\"text-align: center;\"><strong>鱼目混珠</strong><br></p><p style=\"text-align: justify; text-indent: 2em;\">古时候，有个名叫满愿的人，收藏着一棵极为罕见的大珍珠。许多人好奇地想jiàn shi（　）一下这颗珍珠的模样，可是满愿从来不肯让人看。</p><p style=\"text-align: justify; text-indent: 2em;\">每当人们对满愿表示羡慕时，满愿的邻居寿量总是轻蔑（miè）地对人们说：“有颗珍珠算什么？我也有，而且比满愿那颗还要好。”可是，他也像满愿一样，从来不肯让别人看他的珍珠。</p><p style=\"text-align: justify; text-indent: 2em;\">人们虽然从来没见过他们珍藏的珠宝，但是对此都shēn xìn bù yí（　）。于是，大家对两位珍珠的主人羡慕不已。</p><p style=\"text-align: justify; text-indent: 2em;\">后来，他俩忽然同时患（huàn）病。医生看过他们的病后，告诉他们说，他们得的这种病需要用珍珠的粉末配制一种药来治。两个人听了，治病心切，都把自己珍藏的珍珠拿了出来。人们听说他们拿出了珍珠，当然不肯放过这个yì bǎo yǎn fú（　）的机会，纷纷赶来观看。只见满愿那颗珍珠jīng yíng yuán rùn（　），十分迷人。而寿量那颗呢，原来不过是一颗稍大些的鱼眼睛！</p>","contentDesc":"","analysis":"","subContents":[{"content":"<p>根据拼音写词语。</p><p><span style=\"text-align: justify; text-indent: 32px;\">jiàn shi</span>__$$__</p><p><span style=\"text-align: justify; text-indent: 32px;\">shēn xìn bù yí__$$__</span></p><p><span style=\"text-align: justify; text-indent: 32px;\"><span style=\"text-align: justify; text-indent: 32px;\">yì bǎo yǎn fú__$$__</span></span></p><p><span style=\"text-align: justify; text-indent: 32px;\"><span style=\"text-align: justify; text-indent: 32px;\"><span style=\"text-align: justify; text-indent: 32px;\">jīng yíng yuán rùn__$$__</span></span></span></p>","answers":[{"answer":"见识","subAnswers":["见识"],"richTexts":null,"scorePercentage":1,"classification":"","knowledgePoints":null,"knowledgePointsNew":[],"testMethods":[],"solutionMethods":[],"classificationListenUrl":null},{"answer":"深信不疑","subAnswers":["深信不疑"],"richTexts":null,"scorePercentage":1,"classification":"","knowledgePoints":null,"knowledgePointsNew":[{"id":"KP_10100080034014","tagId":0,"main":1,"featureIds":[]}],"testMethods":[{"id":"TM_10100000636722","main":1}],"solutionMethods":[],"classificationListenUrl":null},{"answer":"一饱眼福","subAnswers":["一饱眼福"],"richTexts":null,"scorePercentage":1,"classification":"","knowledgePoints":null,"knowledgePointsNew":[],"testMethods":[{"id":"TM_10100000636722","main":1}],"solutionMethods":[],"classificationListenUrl":null},{"answer":"晶莹圆润","subAnswers":["晶莹圆润"],"richTexts":null,"scorePercentage":1,"classification":"","knowledgePoints":null,"knowledgePointsNew":[],"testMethods":[],"solutionMethods":[],"classificationListenUrl":null}],"subContentTypeId":4,"analysis":"","optionType":"word","options":[],"hideOptionNumber":0,"listenUrl":"","listenName":"","listenSeconds":0,"exploreSeconds":0,"answersSeconds":0,"oralDict":{"seconds":null,"variables":null,"keywords":null,"options":null,"voiceText":null,"sentencePatterns":null,"picUrl":null,"picName":null,"beginListenUrl":null,"endListenUrl":null,"scorePercentage":null,"readySeconds":null,"listenFile":null,"contentDesc":null,"answers":null,"voiceTextsNew":null,"jsgf":null,"videoUrl":null,"videoCoverUrl":null,"highlightPos":null},"submitWays":[0],"tags":[101006],"analysisList":null,"pictureUrl":"","extras":{},"tagsDesc":["其他"]},{"content":"<p>根据解释从文中找出合适的词。</p><p>（1）对自己所不了解的事物觉得新奇而感兴趣。__$$__</p><p>（2）难得见到；很少见到。__$$__</p><p>（3）轻视；不放在眼里。__$$__</p><p>（4）收集保藏。__$$__</p>","answers":[{"answer":"好奇","subAnswers":["好奇"],"richTexts":null,"scorePercentage":1,"classification":"","knowledgePoints":null,"knowledgePointsNew":[{"id":"KP_10100074476085","tagId":0,"main":1,"featureIds":[]}],"testMethods":[{"id":"TM_10100003182846","main":1}],"solutionMethods":[],"classificationListenUrl":null},{"answer":"罕见","subAnswers":["罕见"],"richTexts":null,"scorePercentage":1,"classification":"","knowledgePoints":null,"knowledgePointsNew":[{"id":"KP_10100096166797","tagId":0,"main":1,"featureIds":[]}],"testMethods":[{"id":"TM_10100003182846","main":1}],"solutionMethods":[],"classificationListenUrl":null},{"answer":"轻蔑","subAnswers":["轻蔑"],"richTexts":null,"scorePercentage":1,"classification":"","knowledgePoints":null,"knowledgePointsNew":[{"id":"KP_10100075524414","tagId":0,"main":1,"featureIds":[]}],"testMethods":[{"id":"TM_10100003182846","main":1}],"solutionMethods":[],"classificationListenUrl":null},{"answer":"收藏","subAnswers":["收藏"],"richTexts":null,"scorePercentage":1,"classification":"","knowledgePoints":null,"knowledgePointsNew":[{"id":"KP_10100075638498","tagId":0,"main":1,"featureIds":[]}],"testMethods":[{"id":"TM_10100003182846","main":1}],"solutionMethods":[],"classificationListenUrl":null}],"subContentTypeId":4,"analysis":"","optionType":"word","options":[],"hideOptionNumber":0,"listenUrl":"","listenName":"","listenSeconds":0,"exploreSeconds":0,"answersSeconds":0,"oralDict":{"seconds":null,"variables":null,"keywords":null,"options":null,"voiceText":null,"sentencePatterns":null,"picUrl":null,"picName":null,"beginListenUrl":null,"endListenUrl":null,"scorePercentage":null,"readySeconds":null,"listenFile":null,"contentDesc":null,"answers":null,"voiceTextsNew":null,"jsgf":null,"videoUrl":null,"videoCoverUrl":null,"highlightPos":null},"submitWays":[0],"tags":[101006],"analysisList":null,"pictureUrl":"","extras":{},"tagsDesc":["其他"]},{"content":"<p>根据短文内容填空。</p><p style=\"text-indent: 2em;\">故事中两个人的“珍珠”，一颗是__$$__的真珍珠，另一颗只是__$$__的鱼眼睛。</p>","answers":[{"answer":"1","subAnswers":[],"richTexts":null,"scorePercentage":1,"classification":"","knowledgePoints":null,"knowledgePointsNew":[],"testMethods":[],"solutionMethods":[],"classificationListenUrl":null},{"answer":"0","subAnswers":[],"richTexts":null,"scorePercentage":1,"classification":"","knowledgePoints":null,"knowledgePointsNew":[],"testMethods":[],"solutionMethods":[],"classificationListenUrl":null}],"subContentTypeId":10,"analysis":"","optionType":"word","options":[{"option":"稍大些","file":{"fileId":"","url":"","filename":"","seconds":0}},{"option":"晶莹圆润","file":{"fileId":"","url":"","filename":"","seconds":0}}],"hideOptionNumber":0,"listenUrl":"","listenName":"","listenSeconds":0,"exploreSeconds":0,"answersSeconds":0,"oralDict":{"seconds":null,"variables":null,"keywords":null,"options":null,"voiceText":null,"sentencePatterns":null,"picUrl":null,"picName":null,"beginListenUrl":null,"endListenUrl":null,"scorePercentage":null,"readySeconds":null,"listenFile":null,"contentDesc":null,"answers":null,"voiceTextsNew":null,"jsgf":null,"videoUrl":null,"videoCoverUrl":null,"highlightPos":null},"submitWays":[0],"tags":[101007],"analysisList":null,"pictureUrl":"","extras":{},"tagsDesc":["其他"]},{"content":"《鱼目混珠》这则故事告诉我们：（　）","answers":[{"answer":"2","subAnswers":[],"richTexts":null,"scorePercentage":1,"classification":"","knowledgePoints":null,"knowledgePointsNew":[],"testMethods":[],"solutionMethods":[],"classificationListenUrl":null}],"subContentTypeId":1,"analysis":"","optionType":"sentence","options":[{"option":"鱼目与珍珠很像，不容易区别。","file":{"fileId":"","url":"","filename":"","seconds":0}},{"option":"不能把鱼目当成珍珠去骗人。","file":{"fileId":"","url":"","filename":"","seconds":0}},{"option":"不能以次充好，以假乱真。","file":{"fileId":"","url":"","filename":"","seconds":0}}],"hideOptionNumber":0,"listenUrl":"","listenName":"","listenSeconds":0,"exploreSeconds":0,"answersSeconds":0,"oralDict":{"seconds":null,"variables":null,"keywords":null,"options":null,"voiceText":null,"sentencePatterns":null,"picUrl":null,"picName":null,"beginListenUrl":null,"endListenUrl":null,"scorePercentage":null,"readySeconds":null,"listenFile":null,"contentDesc":null,"answers":null,"voiceTextsNew":null,"jsgf":null,"videoUrl":null,"videoCoverUrl":null,"highlightPos":null},"submitWays":[0],"tags":[101007],"analysisList":null,"pictureUrl":"","extras":{},"tagsDesc":["其他"]}]},"docId":"Q_10110621786524","version":2,"wordId":null,"pictureUrl":null,"tagId":null,"createdAt":1506440673084,"deletedAt":null,"olCreatedAt":1509778066844,"olUpdatedAt":1509778066844,"sentenceIds":null,"sentenceContents":null,"practiceTypeIds":null,"categoryId":0,"fromId":7,"paragraph":null,"articleName":null,"descriptionFile":{"fileId":"","url":"","filename":"","seconds":0},"analysisSeconds":0,"readySeconds":0,"wikiType":null,"others":{"writing_style":"AC_20300000283078"},"skillIds":null,"weighted":null,"additions":null,"answers":[["见识","深信不疑","一饱眼福","晶莹圆润"],["好奇","罕见","轻蔑","收藏"],["1","0"],["2"]],"tags":[101006,101007]}]}}}