{"success":true,"result":{"Q_10108616400056-3":{"resources":[],"questions":[{"id":"Q_10108616400056-3","subjectId":101,"knowledgePoints":null,"knowledgePointsNew":[],"testMethods":[{"id":"TM_10100000672366","main":1}],"solutionMethods":[],"resourceIds":null,"resourceIndex":0,"listenUrl":null,"listenName":null,"listenSeconds":0,"exploreSeconds":0,"answersSeconds":0,"paperIds":["P_10100123505579-3"],"books":null,"booksNew":null,"contentTypeId":1010008,"contentType2Id":0,"difficultyInt":3,"description":"阅读课文《稻草人》片段，完成后面的练习","notFitMobile":0,"seconds":83,"complex":1,"nid":null,"lastEditorId":null,"finalAuditorId":null,"roughAuditorIds":null,"content":{"content":"<p style=\"text-indent: 2em;\">稻草人正在想的时候，一个小蛾飞来，是灰褐色的小蛾。他立刻认出那小蛾是稻子的仇敌，也就是主人的仇敌。从他的职务想，从他对主人的感情想，都必须把那小蛾赶跑了才是。于是，他手里的扇子摇动起来。可是扇子的风很有限，不能够叫小蛾害怕。那小蛾飞了一会儿，落在一片稻叶上，简直像不觉得稻草人在那里驱逐似的。稻草人见小蛾落下了，心里非常着急。可是他的身子跟树木一样，定在泥土里，想往前移动半步也做不到；扇子尽管扇动，那小蛾却依旧稳稳地歇着。<span style=\"text-decoration: underline;\">他想到将来田里的情形，想到主人的眼泪和干瘪的脸，又想到主人的命运，心里就像刀割一样。</span>但是那小蛾是歇定了，不管怎么赶，他就是不动。</p>","contentDesc":"","analysis":"","subContents":[{"content":"<p>从选文中找出下列词语的近义词。</p><p>马上——__$$__</p><p>驱赶——__$$__</p><p>焦急——__$$__</p><p>仍旧——__$$__</p>","answers":[{"answer":"立刻","subAnswers":["立刻"],"richTexts":null,"scorePercentage":1,"classification":"","knowledgePoints":null,"knowledgePointsNew":[{"id":"KP_10100075614030","tagId":0,"main":1,"featureIds":[]}],"testMethods":[{"id":"TM_10100000631040","main":1}],"solutionMethods":[],"classificationListenUrl":null},{"answer":"驱逐","subAnswers":["驱逐"],"richTexts":null,"scorePercentage":1,"classification":"","knowledgePoints":null,"knowledgePointsNew":[{"id":"KP_10100076846718","tagId":0,"main":1,"featureIds":[]}],"testMethods":[{"id":"TM_10100000631040","main":1}],"solutionMethods":[],"classificationListenUrl":null},{"answer":"着急","subAnswers":["着急"],"richTexts":null,"scorePercentage":1,"classification":"","knowledgePoints":null,"knowledgePointsNew":[{"id":"KP_10100075544739","tagId":0,"main":1,"featureIds":[]}],"testMethods":[{"id":"TM_10100000631040","main":1}],"solutionMethods":[],"classificationListenUrl":null},{"answer":"依旧","subAnswers":["依旧"],"richTexts":null,"scorePercentage":1,"classification":"","knowledgePoints":null,"knowledgePointsNew":[{"id":"KP_10100077544618","tagId":0,"main":1,"featureIds":[]}],"testMethods":[{"id":"TM_10100000631040","main":1}],"solutionMethods":[],"classificationListenUrl":null}],"subContentTypeId":4,"analysis":"","optionType":"word","options":[],"hideOptionNumber":0,"listenUrl":"","listenName":"","listenSeconds":0,"exploreSeconds":0,"answersSeconds":0,"oralDict":{"seconds":null,"variables":null,"keywords":null,"options":null,"voiceText":null,"sentencePatterns":null,"picUrl":null,"picName":null,"beginListenUrl":null,"endListenUrl":null,"scorePercentage":null,"readySeconds":null,"listenFile":null,"contentDesc":null,"answers":null,"voiceTextsNew":null,"jsgf":null,"videoUrl":null,"videoCoverUrl":null,"highlightPos":null},"submitWays":[0],"tags":[101006],"analysisList":null,"pictureUrl":"","extras":{},"tagsDesc":["其他"]},{"content":"选文中画线的句子运用__$$__和拟人的修辞手法，写出了稻草人__$$__的心情。稻草人“心里就像刀割一样”不是因为__$$__。","answers":[{"answer":"4","subAnswers":[],"richTexts":null,"scorePercentage":1,"classification":"","knowledgePoints":null,"knowledgePointsNew":[],"testMethods":[],"solutionMethods":[],"classificationListenUrl":null},{"answer":"6","subAnswers":[],"richTexts":null,"scorePercentage":1,"classification":"","knowledgePoints":null,"knowledgePointsNew":[],"testMethods":[],"solutionMethods":[],"classificationListenUrl":null},{"answer":"1","subAnswers":[],"richTexts":null,"scorePercentage":1,"classification":"","knowledgePoints":null,"knowledgePointsNew":[],"testMethods":[],"solutionMethods":[],"classificationListenUrl":null}],"subContentTypeId":10,"analysis":"","optionType":"sentence","options":[{"option":"他想到了将来田里可怕的情形","file":{"fileId":"","url":"","filename":"","seconds":0}},{"option":"他想到小蛾是稻子和主人的仇敌","file":{"fileId":"","url":"","filename":"","seconds":0}},{"option":"他想到了主人的眼泪和干瘪的脸","file":{"fileId":"","url":"","filename":"","seconds":0}},{"option":"他想到了主人将来的悲惨命运","file":{"fileId":"","url":"","filename":"","seconds":0}},{"option":"比喻","file":{"fileId":"","url":"","filename":"","seconds":0}},{"option":"夸张","file":{"fileId":"","url":"","filename":"","seconds":0}},{"option":"痛苦","file":{"fileId":"","url":"","filename":"","seconds":0}},{"option":"开心","file":{"fileId":"","url":"","filename":"","seconds":0}}],"hideOptionNumber":0,"listenUrl":"","listenName":"","listenSeconds":0,"exploreSeconds":0,"answersSeconds":0,"oralDict":{"seconds":null,"variables":null,"keywords":null,"options":null,"voiceText":null,"sentencePatterns":null,"picUrl":null,"picName":null,"beginListenUrl":null,"endListenUrl":null,"scorePercentage":null,"readySeconds":null,"listenFile":null,"contentDesc":null,"answers":null,"voiceTextsNew":null,"jsgf":null,"videoUrl":null,"videoCoverUrl":null,"highlightPos":null},"submitWays":[0],"tags":[101007],"analysisList":null,"pictureUrl":"","extras":{},"tagsDesc":["其他"]}]},"docId":"Q_10108616400056","version":3,"wordId":null,"pictureUrl":null,"tagId":null,"createdAt":1501041447793,"deletedAt":null,"olCreatedAt":1509650531843,"olUpdatedAt":1509650531843,"sentenceIds":null,"sentenceContents":null,"practiceTypeIds":null,"categoryId":0,"fromId":7,"paragraph":null,"articleName":null,"descriptionFile":{"fileId":"","url":"","filename":"","seconds":0},"analysisSeconds":0,"readySeconds":0,"wikiType":null,"others":{"writing_style":"AC_20300000283078"},"skillIds":null,"weighted":null,"additions":null,"answers":[["立刻","驱逐","着急","依旧"],["4","6","1"]],"tags":[101006,101007]}]}}}