{"success":true,"result":{"Q_10109289344325-1":{"resources":[],"questions":[{"id":"Q_10109289344325-1","subjectId":101,"knowledgePoints":null,"knowledgePointsNew":[],"testMethods":[{"id":"TM_10100000672366","main":1}],"solutionMethods":[],"resourceIds":null,"resourceIndex":0,"listenUrl":null,"listenName":null,"listenSeconds":0,"exploreSeconds":0,"answersSeconds":0,"paperIds":["P_10100128215271-1","P_10100128215271-2","P_10100128215271-3","P_10100128215271-4","P_10100128215271-5"],"books":null,"booksNew":null,"contentTypeId":1010008,"contentType2Id":0,"difficultyInt":3,"description":"阅读课内课文片段，回答问题","notFitMobile":0,"seconds":540,"complex":1,"nid":null,"lastEditorId":null,"finalAuditorId":null,"roughAuditorIds":null,"content":{"content":"<p style=\"text-indent: 2em;\">原来她的车胎瘪了，乔依让她坐进车里，自己爬进她的车底下找了一块地方放置千斤顶。他的脚腕被<span style=\"text-decoration: underline;\">蹭</span>（cèng　zèng）破了，因为他没穿袜子。为了干活方便，他摘下了破手套，两只手冻得几乎没有知觉。他<span style=\"text-decoration: underline;\">喘</span>（chuǎn　cuǎn）着粗气，清水鼻涕也流下来了，呼出的一点点热气才使脸没被冻僵。他的手蹭破了，也顾不上擦流出的血。当他干完活时，两只手上沾满了油污，衣服也更脏了。</p>","contentDesc":"","analysis":"","subContents":[{"content":"<p>给画线字选择正确的读音。</p><p>他的脚腕被<span style=\"text-decoration: underline;\">蹭</span>破了<br></p>","answers":[{"answer":"0","subAnswers":[],"richTexts":null,"scorePercentage":1,"classification":"","knowledgePoints":null,"knowledgePointsNew":[{"id":"KP_10100048243387","tagId":0,"main":1,"featureIds":["KPF_10100000004118"]}],"testMethods":[],"solutionMethods":[],"classificationListenUrl":null}],"subContentTypeId":1,"analysis":"","optionType":"word","options":[{"option":"cèng","file":{"fileId":"","url":"","filename":"","seconds":0}},{"option":"zèng","file":{"fileId":"","url":"","filename":"","seconds":0}}],"hideOptionNumber":0,"listenUrl":"","listenName":"","listenSeconds":0,"exploreSeconds":0,"answersSeconds":0,"oralDict":{"seconds":null,"variables":null,"keywords":null,"options":null,"voiceText":null,"sentencePatterns":null,"picUrl":null,"picName":null,"beginListenUrl":null,"endListenUrl":null,"scorePercentage":null,"readySeconds":null,"listenFile":null,"contentDesc":null,"answers":null,"voiceTextsNew":null,"jsgf":null,"videoUrl":null,"videoCoverUrl":null,"highlightPos":null},"submitWays":[0],"tags":[101005],"analysisList":null,"pictureUrl":"","extras":{},"tagsDesc":["其他"]},{"content":"<p style=\"white-space: normal;\">给画线字选择正确的读音。</p><p style=\"white-space: normal;\">他<span style=\"text-decoration: underline;\">喘</span>着粗气</p>","answers":[{"answer":"0","subAnswers":[],"richTexts":null,"scorePercentage":1,"classification":"","knowledgePoints":null,"knowledgePointsNew":[{"id":"KP_10100048505607","tagId":0,"main":1,"featureIds":["KPF_10100000004118"]}],"testMethods":[{"id":"TM_10100000620344","main":1}],"solutionMethods":[],"classificationListenUrl":null}],"subContentTypeId":1,"analysis":"","optionType":"word","options":[{"option":"chuǎn","file":{"fileId":"","url":"","filename":"","seconds":0}},{"option":"cuǎn","file":{"fileId":"","url":"","filename":"","seconds":0}}],"hideOptionNumber":0,"listenUrl":"","listenName":"","listenSeconds":0,"exploreSeconds":0,"answersSeconds":0,"oralDict":{"seconds":null,"variables":null,"keywords":null,"options":null,"voiceText":null,"sentencePatterns":null,"picUrl":null,"picName":null,"beginListenUrl":null,"endListenUrl":null,"scorePercentage":null,"readySeconds":null,"listenFile":null,"contentDesc":null,"answers":null,"voiceTextsNew":null,"jsgf":null,"videoUrl":null,"videoCoverUrl":null,"highlightPos":null},"submitWays":[0],"tags":[101005],"analysisList":null,"pictureUrl":"","extras":{},"tagsDesc":["其他"]},{"content":"<p>选择句子填空。</p><p>因为__$$__，所以__$$__。</p>","answers":[{"answer":"1","subAnswers":[],"richTexts":null,"scorePercentage":1,"classification":"","knowledgePoints":null,"knowledgePointsNew":[],"testMethods":[],"solutionMethods":[],"classificationListenUrl":null},{"answer":"0","subAnswers":[],"richTexts":null,"scorePercentage":1,"classification":"","knowledgePoints":null,"knowledgePointsNew":[],"testMethods":[],"solutionMethods":[],"classificationListenUrl":null}],"subContentTypeId":10,"analysis":"","optionType":"sentence","options":[{"option":"他的脚腕被蹭破了","file":{"fileId":"","url":"","filename":"","seconds":0}},{"option":"他没穿袜子","file":{"fileId":"","url":"","filename":"","seconds":0}}],"hideOptionNumber":0,"listenUrl":"","listenName":"","listenSeconds":0,"exploreSeconds":0,"answersSeconds":0,"oralDict":{"seconds":null,"variables":null,"keywords":null,"options":null,"voiceText":null,"sentencePatterns":null,"picUrl":null,"picName":null,"beginListenUrl":null,"endListenUrl":null,"scorePercentage":null,"readySeconds":null,"listenFile":null,"contentDesc":null,"answers":null,"voiceTextsNew":null,"jsgf":null,"videoUrl":null,"videoCoverUrl":null,"highlightPos":null},"submitWays":[0],"tags":[101007],"analysisList":null,"pictureUrl":"","extras":{},"tagsDesc":["其他"]}]},"docId":"Q_10109289344325","version":1,"wordId":null,"pictureUrl":null,"tagId":null,"createdAt":1502193641521,"deletedAt":null,"olCreatedAt":1503571195833,"olUpdatedAt":1503571195833,"sentenceIds":null,"sentenceContents":null,"practiceTypeIds":null,"categoryId":0,"fromId":7,"paragraph":null,"articleName":null,"descriptionFile":{"fileId":"","url":"","filename":"","seconds":0},"analysisSeconds":0,"readySeconds":0,"wikiType":null,"others":{"writing_style":"AC_20300000283078"},"skillIds":null,"weighted":null,"additions":null,"answers":[["0"],["0"],["1","0"]],"tags":[101005,101007]}]}}}