{"success":true,"result":{"Q_10108602052075-2":{"resources":[],"questions":[{"id":"Q_10108602052075-2","subjectId":101,"knowledgePoints":null,"knowledgePointsNew":[],"testMethods":[{"id":"TM_10100000672366","main":1}],"solutionMethods":[],"resourceIds":null,"resourceIndex":0,"listenUrl":null,"listenName":null,"listenSeconds":0,"exploreSeconds":0,"answersSeconds":0,"paperIds":["P_10100123241249-1","P_10100123241249-2","P_10100123241249-3","P_10100123241249-4","P_10100123241249-5","P_10100123241249-6","P_10100123241249-7","P_10100123241249-8"],"books":null,"booksNew":null,"contentTypeId":1010008,"contentType2Id":0,"difficultyInt":3,"description":"阅读课文《凡卡》的片段，回答问题","notFitMobile":0,"seconds":480,"complex":1,"nid":null,"lastEditorId":null,"finalAuditorId":null,"roughAuditorIds":null,"content":{"content":"<p style=\"text-indent: 2em;\">“昨天晚上我挨了一顿打，因为我给他们的小崽子摇摇篮的时候，不知不觉睡着了。 老板揪着我的头发，把我拖到院子里，拿皮带揍了我一顿。这个礼拜，老板娘叫我收拾一条青鱼，她在旁边监督我，我从尾巴上弄起，她就捞起那条青鱼，拿鱼嘴直戳我的脸。伙计们捉弄我，他们打发我上酒店去打酒，他们叫我偷老板的黄瓜，老板随手捞起个家伙就打我。吃的呢，简直没有。早晨吃一点儿面包，午饭是稀粥，晚上又是一点儿面包；至于菜啦，茶啦，只有老板自己才大吃大喝。他们叫我睡在过道里，他们的小崽子一哭，我就别想睡觉，只好摇那个摇篮。亲爱的爷爷，发发慈悲吧，带我离开这儿回家，回到我们村子里去吧！我再也受不住了！……我给您跪下了，我会永远为您祈祷。带我离开这儿吧，要不，我就要死了！……” </p>","contentDesc":"","analysis":"","subContents":[{"content":"<p>为下列词语中的“打”字选择恰当的解释。</p><p><span style=\"text-decoration: underline;\">打</span>酒__$$__</p><p>挨<span style=\"text-decoration: underline;\">打</span>__$$__</p>","answers":[{"answer":"2","subAnswers":[],"richTexts":null,"scorePercentage":1,"classification":"","knowledgePoints":null,"knowledgePointsNew":[],"testMethods":[],"solutionMethods":[],"classificationListenUrl":null},{"answer":"0","subAnswers":[],"richTexts":null,"scorePercentage":1,"classification":"","knowledgePoints":null,"knowledgePointsNew":[],"testMethods":[],"solutionMethods":[],"classificationListenUrl":null}],"subContentTypeId":10,"analysis":"","optionType":"word","options":[{"option":"击","file":{"fileId":"","url":"","filename":"","seconds":0}},{"option":"举","file":{"fileId":"","url":"","filename":"","seconds":0}},{"option":"购买","file":{"fileId":"","url":"","filename":"","seconds":0}}],"hideOptionNumber":0,"listenUrl":"","listenName":"","listenSeconds":0,"exploreSeconds":0,"answersSeconds":0,"oralDict":{"seconds":null,"variables":null,"keywords":null,"options":null,"voiceText":null,"sentencePatterns":null,"picUrl":null,"picName":null,"beginListenUrl":null,"endListenUrl":null,"scorePercentage":null,"readySeconds":null,"listenFile":null,"contentDesc":null,"answers":null,"voiceTextsNew":null,"jsgf":null,"videoUrl":null,"videoCoverUrl":null,"highlightPos":null},"submitWays":[0],"tags":[101007],"analysisList":null,"pictureUrl":"","extras":{},"tagsDesc":["其他"]},{"content":"<p>单选。</p><p>凡卡是从哪几个方面向爷爷诉苦的？</p>","answers":[{"answer":"1","subAnswers":[],"richTexts":null,"scorePercentage":1,"classification":"","knowledgePoints":null,"knowledgePointsNew":[],"testMethods":[],"solutionMethods":[],"classificationListenUrl":null}],"subContentTypeId":1,"analysis":"","optionType":"sentence","options":[{"option":"从挨打、被捉弄、睡不好觉这三个方面。<br>","file":{"fileId":"","url":"","filename":"","seconds":0}},{"option":"从挨打、被捉弄、挨饿、睡不好觉这四个方面。","file":{"fileId":"","url":"","filename":"","seconds":0}}],"hideOptionNumber":0,"listenUrl":"","listenName":"","listenSeconds":0,"exploreSeconds":0,"answersSeconds":0,"oralDict":{"seconds":null,"variables":null,"keywords":null,"options":null,"voiceText":null,"sentencePatterns":null,"picUrl":null,"picName":null,"beginListenUrl":null,"endListenUrl":null,"scorePercentage":null,"readySeconds":null,"listenFile":null,"contentDesc":null,"answers":null,"voiceTextsNew":null,"jsgf":null,"videoUrl":null,"videoCoverUrl":null,"highlightPos":null},"submitWays":[0],"tags":[101007],"analysisList":null,"pictureUrl":"","extras":{},"tagsDesc":["其他"]}]},"docId":"Q_10108602052075","version":2,"wordId":null,"pictureUrl":null,"tagId":null,"createdAt":1500995308960,"deletedAt":null,"olCreatedAt":1502872687486,"olUpdatedAt":1502872687486,"sentenceIds":null,"sentenceContents":null,"practiceTypeIds":null,"categoryId":0,"fromId":7,"paragraph":null,"articleName":null,"descriptionFile":{"fileId":"","url":"","filename":"","seconds":0},"analysisSeconds":0,"readySeconds":0,"wikiType":null,"others":{"writing_style":"AC_20300000283078"},"skillIds":null,"weighted":null,"additions":null,"answers":[["2","0"],["1"]],"tags":[101007]}]}}}