{"success":true,"result":{"Q_10110017274306-2":{"resources":[],"questions":[{"id":"Q_10110017274306-2","subjectId":101,"knowledgePoints":null,"knowledgePointsNew":[],"testMethods":[{"id":"TM_10100000673226","main":1}],"solutionMethods":[],"resourceIds":null,"resourceIndex":0,"listenUrl":null,"listenName":null,"listenSeconds":0,"exploreSeconds":0,"answersSeconds":0,"paperIds":["P_10100130128902-3"],"books":null,"booksNew":null,"contentTypeId":1010008,"contentType2Id":0,"difficultyInt":4,"description":"阅读课外诗歌，回答问题","notFitMobile":0,"seconds":600,"complex":1,"nid":null,"lastEditorId":null,"finalAuditorId":null,"roughAuditorIds":null,"content":{"content":"<p style=\"text-align: center;\"><strong>山里的孩子</strong></p><p style=\"text-align: center; text-indent: 0em;\">每当公鸡唤出黎明<strong><br></strong></p><p style=\"text-align: center; text-indent: 0em;\">山里的孩子</p><p style=\"text-align: center; text-indent: 0em;\">便会坐在牛背上</p><p style=\"text-align: center; text-indent: 0em;\">阅读晨曦这本精致的诗集</p><p style=\"text-align: center; text-indent: 0em;\">蝴蝶编出精彩的情节</p><p style=\"text-align: center; text-indent: 0em;\">燕子衔来呢喃的标点</p><p style=\"text-indent: 2em;\"><br></p><p style=\"text-align: center; text-indent: 0em;\">喜鹊朗读优美的韵调</p><p style=\"text-align: center; text-indent: 0em;\">每当夕阳西下</p><p style=\"text-align: center; text-indent: 0em;\">山里的孩子</p><p style=\"text-align: center; text-indent: 0em;\">挎着装满蘑菇的竹篮</p><p style=\"text-align: center; text-indent: 0em;\">把幸福的歌儿</p><p style=\"text-align: center; text-indent: 0em;\">印在一路的绿叶红花上</p><p style=\"text-align: center; text-indent: 0em;\">一不小心</p><p style=\"text-align: center; text-indent: 0em;\">带回了一个亮堂堂的月亮</p><p style=\"text-indent: 2em;\"><br></p><p style=\"text-align: center; text-indent: 0em;\">每当细雨蒙蒙</p><p style=\"text-align: center; text-indent: 0em;\">山里的孩子</p><p style=\"text-align: center; text-indent: 0em;\">盯着碧绿的葵叶</p><p style=\"text-align: center; text-indent: 0em;\">光着脚丫</p><p style=\"text-align: center; text-indent: 0em;\">踩一路歪歪的泥印儿</p><p style=\"text-align: center; text-indent: 0em;\">在河边　在水洼</p><p style=\"text-align: center; text-indent: 0em;\">追着雨娃娃长大</p><p style=\"text-indent: 2em;\"><br></p><p style=\"text-align: center; text-indent: 0em;\">山里的孩子</p><p style=\"text-align: center; text-indent: 0em;\">每一天　每一年</p><p style=\"text-align: center; text-indent: 0em;\">扯着清凉的山风</p><p style=\"text-align: center; text-indent: 0em;\">背着晶莹的雨水</p><p style=\"text-align: center; text-indent: 0em;\">忘记了自己的成长</p>","contentDesc":"","analysis":"","subContents":[{"content":"<p>根据原文内容，按顺序填空。</p><p>诗歌有__$$__（填阿拉伯数字）小节，第一、二小节描写了山里的孩子清晨放__$$__、傍晚采__$$__的事。</p>","answers":[{"answer":"4","subAnswers":["4"],"richTexts":null,"scorePercentage":1,"classification":"","knowledgePoints":null,"knowledgePointsNew":[],"testMethods":[],"solutionMethods":[],"classificationListenUrl":null},{"answer":"牛","subAnswers":["牛"],"richTexts":null,"scorePercentage":1,"classification":"","knowledgePoints":null,"knowledgePointsNew":[],"testMethods":[],"solutionMethods":[],"classificationListenUrl":null},{"answer":"蘑菇","subAnswers":["蘑菇"],"richTexts":null,"scorePercentage":1,"classification":"","knowledgePoints":null,"knowledgePointsNew":[],"testMethods":[],"solutionMethods":[],"classificationListenUrl":null}],"subContentTypeId":4,"analysis":"","optionType":"word","options":[],"hideOptionNumber":0,"listenUrl":"","listenName":"","listenSeconds":0,"exploreSeconds":0,"answersSeconds":0,"oralDict":{"seconds":null,"variables":null,"keywords":null,"options":null,"voiceText":null,"sentencePatterns":null,"picUrl":null,"picName":null,"beginListenUrl":null,"endListenUrl":null,"scorePercentage":null,"readySeconds":null,"listenFile":null,"contentDesc":null,"answers":null,"voiceTextsNew":null,"jsgf":null,"videoUrl":null,"videoCoverUrl":null,"highlightPos":null},"submitWays":[0],"tags":[101007],"analysisList":null,"pictureUrl":"","extras":{},"tagsDesc":["其他"]},{"content":"<p>根据原文内容，按顺序填空。</p><p>最后一小节中表示动作的词有：__$$__、__$$__、忘记等（填单个汉字）</p>","answers":[{"answer":"扯","subAnswers":["扯"],"richTexts":null,"scorePercentage":1,"classification":"","knowledgePoints":null,"knowledgePointsNew":[{"id":"KP_10100049169624","tagId":0,"main":1,"featureIds":["KPF_10100000005852"]}],"testMethods":[{"id":"TM_10100003200844","main":1}],"solutionMethods":[],"classificationListenUrl":null},{"answer":"背","subAnswers":["背"],"richTexts":null,"scorePercentage":1,"classification":"","knowledgePoints":null,"knowledgePointsNew":[{"id":"KP_10100047591732","tagId":0,"main":1,"featureIds":["KPF_10100000005852"]}],"testMethods":[{"id":"TM_10100003200844","main":1}],"solutionMethods":[],"classificationListenUrl":null}],"subContentTypeId":4,"analysis":"","optionType":"word","options":[],"hideOptionNumber":0,"listenUrl":"","listenName":"","listenSeconds":0,"exploreSeconds":0,"answersSeconds":0,"oralDict":{"seconds":null,"variables":null,"keywords":null,"options":null,"voiceText":null,"sentencePatterns":null,"picUrl":null,"picName":null,"beginListenUrl":null,"endListenUrl":null,"scorePercentage":null,"readySeconds":null,"listenFile":null,"contentDesc":null,"answers":null,"voiceTextsNew":null,"jsgf":null,"videoUrl":null,"videoCoverUrl":null,"highlightPos":null},"submitWays":[0],"tags":[101005],"analysisList":null,"pictureUrl":"","extras":{},"tagsDesc":["其他"]}]},"docId":"Q_10110017274306","version":2,"wordId":null,"pictureUrl":null,"tagId":null,"createdAt":1503233323052,"deletedAt":null,"olCreatedAt":1509772031946,"olUpdatedAt":1509772031946,"sentenceIds":null,"sentenceContents":null,"practiceTypeIds":null,"categoryId":0,"fromId":7,"paragraph":null,"articleName":null,"descriptionFile":{"fileId":"","url":"","filename":"","seconds":0},"analysisSeconds":0,"readySeconds":0,"wikiType":null,"others":{"writing_style":"AC_20300000283078"},"skillIds":null,"weighted":null,"additions":null,"answers":[["4","牛","蘑菇"],["扯","背"]],"tags":[101007,101005]}]}}}{"success":true,"result":{"Q_10110017274306-2":{"resources":[],"questions":[{"id":"Q_10110017274306-2","subjectId":101,"knowledgePoints":null,"knowledgePointsNew":[],"testMethods":[{"id":"TM_10100000673226","main":1}],"solutionMethods":[],"resourceIds":null,"resourceIndex":0,"listenUrl":null,"listenName":null,"listenSeconds":0,"exploreSeconds":0,"answersSeconds":0,"paperIds":["P_10100130128902-3"],"books":null,"booksNew":null,"contentTypeId":1010008,"contentType2Id":0,"difficultyInt":4,"description":"阅读课外诗歌，回答问题","notFitMobile":0,"seconds":600,"complex":1,"nid":null,"lastEditorId":null,"finalAuditorId":null,"roughAuditorIds":null,"content":{"content":"<p style=\"text-align: center;\"><strong>山里的孩子</strong></p><p style=\"text-align: center; text-indent: 0em;\">每当公鸡唤出黎明<strong><br></strong></p><p style=\"text-align: center; text-indent: 0em;\">山里的孩子</p><p style=\"text-align: center; text-indent: 0em;\">便会坐在牛背上</p><p style=\"text-align: center; text-indent: 0em;\">阅读晨曦这本精致的诗集</p><p style=\"text-align: center; text-indent: 0em;\">蝴蝶编出精彩的情节</p><p style=\"text-align: center; text-indent: 0em;\">燕子衔来呢喃的标点</p><p style=\"text-indent: 2em;\"><br></p><p style=\"text-align: center; text-indent: 0em;\">喜鹊朗读优美的韵调</p><p style=\"text-align: center; text-indent: 0em;\">每当夕阳西下</p><p style=\"text-align: center; text-indent: 0em;\">山里的孩子</p><p style=\"text-align: center; text-indent: 0em;\">挎着装满蘑菇的竹篮</p><p style=\"text-align: center; text-indent: 0em;\">把幸福的歌儿</p><p style=\"text-align: center; text-indent: 0em;\">印在一路的绿叶红花上</p><p style=\"text-align: center; text-indent: 0em;\">一不小心</p><p style=\"text-align: center; text-indent: 0em;\">带回了一个亮堂堂的月亮</p><p style=\"text-indent: 2em;\"><br></p><p style=\"text-align: center; text-indent: 0em;\">每当细雨蒙蒙</p><p style=\"text-align: center; text-indent: 0em;\">山里的孩子</p><p style=\"text-align: center; text-indent: 0em;\">盯着碧绿的葵叶</p><p style=\"text-align: center; text-indent: 0em;\">光着脚丫</p><p style=\"text-align: center; text-indent: 0em;\">踩一路歪歪的泥印儿</p><p style=\"text-align: center; text-indent: 0em;\">在河边　在水洼</p><p style=\"text-align: center; text-indent: 0em;\">追着雨娃娃长大</p><p style=\"text-indent: 2em;\"><br></p><p style=\"text-align: center; text-indent: 0em;\">山里的孩子</p><p style=\"text-align: center; text-indent: 0em;\">每一天　每一年</p><p style=\"text-align: center; text-indent: 0em;\">扯着清凉的山风</p><p style=\"text-align: center; text-indent: 0em;\">背着晶莹的雨水</p><p style=\"text-align: center; text-indent: 0em;\">忘记了自己的成长</p>","contentDesc":"","analysis":"","subContents":[{"content":"<p>根据原文内容，按顺序填空。</p><p>诗歌有__$$__（填阿拉伯数字）小节，第一、二小节描写了山里的孩子清晨放__$$__、傍晚采__$$__的事。</p>","answers":[{"answer":"4","subAnswers":["4"],"richTexts":null,"scorePercentage":1,"classification":"","knowledgePoints":null,"knowledgePointsNew":[],"testMethods":[],"solutionMethods":[],"classificationListenUrl":null},{"answer":"牛","subAnswers":["牛"],"richTexts":null,"scorePercentage":1,"classification":"","knowledgePoints":null,"knowledgePointsNew":[],"testMethods":[],"solutionMethods":[],"classificationListenUrl":null},{"answer":"蘑菇","subAnswers":["蘑菇"],"richTexts":null,"scorePercentage":1,"classification":"","knowledgePoints":null,"knowledgePointsNew":[],"testMethods":[],"solutionMethods":[],"classificationListenUrl":null}],"subContentTypeId":4,"analysis":"","optionType":"word","options":[],"hideOptionNumber":0,"listenUrl":"","listenName":"","listenSeconds":0,"exploreSeconds":0,"answersSeconds":0,"oralDict":{"seconds":null,"variables":null,"keywords":null,"options":null,"voiceText":null,"sentencePatterns":null,"picUrl":null,"picName":null,"beginListenUrl":null,"endListenUrl":null,"scorePercentage":null,"readySeconds":null,"listenFile":null,"contentDesc":null,"answers":null,"voiceTextsNew":null,"jsgf":null,"videoUrl":null,"videoCoverUrl":null,"highlightPos":null},"submitWays":[0],"tags":[101007],"analysisList":null,"pictureUrl":"","extras":{},"tagsDesc":["其他"]},{"content":"<p>根据原文内容，按顺序填空。</p><p>最后一小节中表示动作的词有：__$$__、__$$__、忘记等（填单个汉字）</p>","answers":[{"answer":"扯","subAnswers":["扯"],"richTexts":null,"scorePercentage":1,"classification":"","knowledgePoints":null,"knowledgePointsNew":[{"id":"KP_10100049169624","tagId":0,"main":1,"featureIds":["KPF_10100000005852"]}],"testMethods":[{"id":"TM_10100003200844","main":1}],"solutionMethods":[],"classificationListenUrl":null},{"answer":"背","subAnswers":["背"],"richTexts":null,"scorePercentage":1,"classification":"","knowledgePoints":null,"knowledgePointsNew":[{"id":"KP_10100047591732","tagId":0,"main":1,"featureIds":["KPF_10100000005852"]}],"testMethods":[{"id":"TM_10100003200844","main":1}],"solutionMethods":[],"classificationListenUrl":null}],"subContentTypeId":4,"analysis":"","optionType":"word","options":[],"hideOptionNumber":0,"listenUrl":"","listenName":"","listenSeconds":0,"exploreSeconds":0,"answersSeconds":0,"oralDict":{"seconds":null,"variables":null,"keywords":null,"options":null,"voiceText":null,"sentencePatterns":null,"picUrl":null,"picName":null,"beginListenUrl":null,"endListenUrl":null,"scorePercentage":null,"readySeconds":null,"listenFile":null,"contentDesc":null,"answers":null,"voiceTextsNew":null,"jsgf":null,"videoUrl":null,"videoCoverUrl":null,"highlightPos":null},"submitWays":[0],"tags":[101005],"analysisList":null,"pictureUrl":"","extras":{},"tagsDesc":["其他"]}]},"docId":"Q_10110017274306","version":2,"wordId":null,"pictureUrl":null,"tagId":null,"createdAt":1503233323052,"deletedAt":null,"olCreatedAt":1509772031946,"olUpdatedAt":1509772031946,"sentenceIds":null,"sentenceContents":null,"practiceTypeIds":null,"categoryId":0,"fromId":7,"paragraph":null,"articleName":null,"descriptionFile":{"fileId":"","url":"","filename":"","seconds":0},"analysisSeconds":0,"readySeconds":0,"wikiType":null,"others":{"writing_style":"AC_20300000283078"},"skillIds":null,"weighted":null,"additions":null,"answers":[["4","牛","蘑菇"],["扯","背"]],"tags":[101007,101005]}]}}}